dmweather/__init__.py
dmweather/core.py
dmweather/exceptions.py
dmweather-0.0.1.dist-info/licenses/LICENSE
dmweather-0.0.1.dist-info/METADATA
dmweather-0.0.1.dist-info/WHEEL
dmweather-0.0.1.dist-info/top_level.txt
dmweather-0.0.1.dist-info/RECORD
