Metadata-Version: 2.4
Name: dmweather
Version: 0.0.1
Summary: Librería Python para obtener información del clima actual y pronósticos
Author-email: Danilo Mosqueira <danilo855984@gmail.com>
Project-URL: Homepage, https://github.com/tu-usuario/dmweather
Project-URL: Bug Tracker, https://github.com/tu-usuario/dmweather/issues
Project-URL: Documentation, https://github.com/tu-usuario/dmweather#readme
Keywords: weather,clima,api,openweathermap,forecast,pronostico
Classifier: Development Status :: 5 - Production/Stable
Classifier: Intended Audience :: Developers
Classifier: Topic :: Software Development :: Libraries :: Python Modules
Classifier: License :: OSI Approved :: MIT License
Classifier: Programming Language :: Python :: 3.7
Classifier: Programming Language :: Python :: 3.8
Classifier: Programming Language :: Python :: 3.9
Classifier: Programming Language :: Python :: 3.10
Classifier: Programming Language :: Python :: 3.11
Classifier: Operating System :: OS Independent
Requires-Python: >=3.7
License-File: LICENSE
Requires-Dist: requests>=2.25.0
Dynamic: license-file
